bytesbufio/__init__.py
bytesbufio/bytes_buffer_io.py
tests/__init__.py
tests/bytes_buffer_io_test.py
tests/bytesio_test.py
bytesbufio-1.0.3.dist-info/METADATA
bytesbufio-1.0.3.dist-info/WHEEL
bytesbufio-1.0.3.dist-info/top_level.txt
bytesbufio-1.0.3.dist-info/RECORD
