Metadata-Version: 2.1
Name: bytesbufio
Version: 1.0.3
Summary: io.BytesIO that preserves bytes after close
Home-page: https://github.com/cbuschka/python-bytesbufio
Author: Cornelius Buschka
Author-email: cbuschka@gmail.com
License: UNKNOWN
Platform: UNKNOWN
Classifier: Programming Language :: Python :: 3
Classifier: License :: OSI Approved :: Apache Software License
Classifier: Operating System :: OS Independent
Requires-Python: >=3.6
